argofloats/__init__.py
argofloats/argofloats.py
argofloats-0.0.7.dist-info/LICENSE
argofloats-0.0.7.dist-info/METADATA
argofloats-0.0.7.dist-info/WHEEL
argofloats-0.0.7.dist-info/entry_points.txt
argofloats-0.0.7.dist-info/top_level.txt
argofloats-0.0.7.dist-info/RECORD
