Metadata-Version: 2.1
Name: argofloats
Version: 0.0.7
Summary: Simple CLI for ArgoVis & Argofloats
Home-page: https://github.com/samapriya/argofloats
Author: Samapriya Roy
Author-email: samapriya.roy@gmail.com
License: Apache 2.0
Platform: UNKNOWN
Classifier: Development Status :: 3 - Alpha
Classifier: Intended Audience :: Developers
Classifier: Intended Audience :: Science/Research
Classifier: Natural Language :: English
Classifier: License :: OSI Approved :: Apache Software License
Classifier: Programming Language :: Python :: 3.6
Classifier: Programming Language :: Python :: 3.7
Classifier: Programming Language :: Python :: 3.8
Classifier: Operating System :: OS Independent
Classifier: Topic :: Scientific/Engineering :: GIS
Requires-Python: >=3.4
Requires-Dist: requests (>=2.24.0)
Requires-Dist: area (>=1.1.1)
Requires-Dist: beautifulsoup4 (>=4.10.0)
Requires-Dist: geojson (>=2.5.0)
Requires-Dist: tenacity (>=8.0.1)
Requires-Dist: pandas (>=1.3.5)
Requires-Dist: pyproj (>=1.9.5.1) ; platform_system != "Windows"
Requires-Dist: shapely (>=1.7.1) ; platform_system != "Windows"
Requires-Dist: fiona (>=1.8.20) ; platform_system != "Windows"
Requires-Dist: geopandas (>=0.9.0) ; platform_system != "Windows"
